{
  "manifest": {
    "schema_version": "1",
    "pack_id": "core_b1",
    "title": {
      "pt": "Base B1",
      "en": "Core B1"
    },
    "theme": "core",
    "level": "B1",
    "language_pair": "pt-BR/en",
    "version": 1,
    "source": "builtin",
    "enabled_by_default": true,
    "dependencies": [],
    "generator_compatibility": {
      "min_version": "1",
      "max_version": "1"
    }
  },
  "lexical_items": [
    {
      "item_id": "core_b1_plan",
      "pack_id": "core_b1",
      "theme": "core",
      "level": "B1",
      "canonical": "plan",
      "translation_pt": "plano",
      "semantic_type": "object",
      "tags": [
        "core",
        "b1"
      ]
    },
    {
      "item_id": "core_b1_answer",
      "pack_id": "core_b1",
      "theme": "core",
      "level": "B1",
      "canonical": "answer",
      "translation_pt": "resposta",
      "semantic_type": "time",
      "tags": [
        "core",
        "b1"
      ]
    },
    {
      "item_id": "core_b1_question",
      "pack_id": "core_b1",
      "theme": "core",
      "level": "B1",
      "canonical": "question",
      "translation_pt": "pergunta",
      "semantic_type": "action",
      "tags": [
        "core",
        "b1"
      ]
    },
    {
      "item_id": "core_b1_idea",
      "pack_id": "core_b1",
      "theme": "core",
      "level": "B1",
      "canonical": "idea",
      "translation_pt": "ideia",
      "semantic_type": "object",
      "tags": [
        "core",
        "b1"
      ]
    },
    {
      "item_id": "core_b1_problem",
      "pack_id": "core_b1",
      "theme": "core",
      "level": "B1",
      "canonical": "problem",
      "translation_pt": "problema",
      "semantic_type": "time",
      "tags": [
        "core",
        "b1"
      ]
    },
    {
      "item_id": "core_b1_word",
      "pack_id": "core_b1",
      "theme": "core",
      "level": "B1",
      "canonical": "word",
      "translation_pt": "palavra",
      "semantic_type": "action",
      "tags": [
        "core",
        "b1"
      ]
    },
    {
      "item_id": "core_b1_name",
      "pack_id": "core_b1",
      "theme": "core",
      "level": "B1",
      "canonical": "name",
      "translation_pt": "nome",
      "semantic_type": "object",
      "tags": [
        "core",
        "b1"
      ]
    },
    {
      "item_id": "core_b1_number",
      "pack_id": "core_b1",
      "theme": "core",
      "level": "B1",
      "canonical": "number",
      "translation_pt": "número",
      "semantic_type": "time",
      "tags": [
        "core",
        "b1"
      ]
    },
    {
      "item_id": "core_b1_place",
      "pack_id": "core_b1",
      "theme": "core",
      "level": "B1",
      "canonical": "place",
      "translation_pt": "lugar",
      "semantic_type": "action",
      "tags": [
        "core",
        "b1"
      ]
    },
    {
      "item_id": "core_b1_time",
      "pack_id": "core_b1",
      "theme": "core",
      "level": "B1",
      "canonical": "time",
      "translation_pt": "horário",
      "semantic_type": "object",
      "tags": [
        "core",
        "b1"
      ]
    },
    {
      "item_id": "core_b1_reason",
      "pack_id": "core_b1",
      "theme": "core",
      "level": "B1",
      "canonical": "reason",
      "translation_pt": "motivo",
      "semantic_type": "time",
      "tags": [
        "core",
        "b1"
      ]
    },
    {
      "item_id": "core_b1_example",
      "pack_id": "core_b1",
      "theme": "core",
      "level": "B1",
      "canonical": "example",
      "translation_pt": "exemplo",
      "semantic_type": "action",
      "tags": [
        "core",
        "b1"
      ]
    },
    {
      "item_id": "core_b1_list",
      "pack_id": "core_b1",
      "theme": "core",
      "level": "B1",
      "canonical": "list",
      "translation_pt": "lista",
      "semantic_type": "object",
      "tags": [
        "core",
        "b1"
      ]
    },
    {
      "item_id": "core_b1_note",
      "pack_id": "core_b1",
      "theme": "core",
      "level": "B1",
      "canonical": "note",
      "translation_pt": "anotação",
      "semantic_type": "time",
      "tags": [
        "core",
        "b1"
      ]
    },
    {
      "item_id": "core_b1_rule",
      "pack_id": "core_b1",
      "theme": "core",
      "level": "B1",
      "canonical": "rule",
      "translation_pt": "regra",
      "semantic_type": "action",
      "tags": [
        "core",
        "b1"
      ]
    },
    {
      "item_id": "core_b1_change",
      "pack_id": "core_b1",
      "theme": "core",
      "level": "B1",
      "canonical": "change",
      "translation_pt": "mudança",
      "semantic_type": "object",
      "tags": [
        "core",
        "b1"
      ]
    },
    {
      "item_id": "core_b1_part",
      "pack_id": "core_b1",
      "theme": "core",
      "level": "B1",
      "canonical": "part",
      "translation_pt": "parte",
      "semantic_type": "time",
      "tags": [
        "core",
        "b1"
      ]
    },
    {
      "item_id": "core_b1_group",
      "pack_id": "core_b1",
      "theme": "core",
      "level": "B1",
      "canonical": "group",
      "translation_pt": "grupo",
      "semantic_type": "action",
      "tags": [
        "core",
        "b1"
      ]
    },
    {
      "item_id": "core_b1_point",
      "pack_id": "core_b1",
      "theme": "core",
      "level": "B1",
      "canonical": "point",
      "translation_pt": "ponto",
      "semantic_type": "object",
      "tags": [
        "core",
        "b1"
      ]
    },
    {
      "item_id": "core_b1_story",
      "pack_id": "core_b1",
      "theme": "core",
      "level": "B1",
      "canonical": "story",
      "translation_pt": "história",
      "semantic_type": "time",
      "tags": [
        "core",
        "b1"
      ]
    }
  ],
  "template_definitions": [
    {
      "template_id": "core_b1_subject_have_past_participle_yet_01",
      "family_id": "core_b1_subject_have_past_participle_yet_0",
      "pack_id": "core_b1",
      "theme": "core",
      "level": "B1",
      "pattern_id": "subject_have_past_participle_yet",
      "primary_skill_id": "present_perfect",
      "skill_ids": [
        "present_perfect",
        "vocabulary"
      ],
      "exercise_types": [
        "translate_natural",
        "fill_blank",
        "build_sentence",
        "choose_best",
        "rewrite_natural",
        "listen_type",
        "speak_sentence"
      ],
      "slots": {
        "subject": "we",
        "object": "core_b1_plan"
      },
      "constraints": [
        "subject_auxiliary_agreement",
        "level_allows_present_perfect_continuous"
      ],
      "distractor_strategies": [
        "wrong_word_order",
        "wrong_tense",
        "wrong_collocation"
      ],
      "sentence": "We have checked the plan already.",
      "source_locale": "pt-BR",
      "source_text_pt": "Nós já verificamos o plano.",
      "target_locale": "en",
      "expected_answers_en": [
        "We have checked the plan already."
      ],
      "accepted_variants_en": [
        "We've checked the plan already."
      ],
      "explanation_pt": "Present perfect com already.",
      "skill_targets": [
        "present_perfect"
      ],
      "pt": "Nós já verificamos o plano.",
      "ctx": "Contexto de base (nível B1).",
      "blank": "have",
      "wrong": "We have check the plan already."
    },
    {
      "template_id": "core_b1_subject_have_been_ving_object_duration_02",
      "family_id": "core_b1_subject_have_been_ving_object_duration_1",
      "pack_id": "core_b1",
      "theme": "core",
      "level": "B1",
      "pattern_id": "subject_have_been_ving_object_duration",
      "primary_skill_id": "present_perfect_continuous",
      "skill_ids": [
        "present_perfect_continuous",
        "vocabulary"
      ],
      "exercise_types": [
        "translate_natural",
        "fill_blank",
        "build_sentence",
        "choose_best",
        "rewrite_natural",
        "listen_type",
        "speak_sentence"
      ],
      "slots": {
        "subject": "we",
        "object": "core_b1_answer"
      },
      "constraints": [
        "subject_auxiliary_agreement",
        "level_allows_present_perfect_continuous"
      ],
      "distractor_strategies": [
        "wrong_word_order",
        "wrong_tense",
        "wrong_collocation"
      ],
      "sentence": "They have been reviewing the answer for two hours.",
      "source_locale": "pt-BR",
      "source_text_pt": "Eles estão revisando a resposta há duas horas.",
      "target_locale": "en",
      "expected_answers_en": [
        "They have been reviewing the answer for two hours."
      ],
      "accepted_variants_en": [
        "They've been reviewing the answer for two hours."
      ],
      "explanation_pt": "Present perfect continuous com duração (for).",
      "skill_targets": [
        "present_perfect_continuous"
      ],
      "pt": "Eles estão revisando a resposta há duas horas.",
      "ctx": "Contexto de base (nível B1).",
      "blank": "have",
      "wrong": "They have been reviewed the answer for two hours."
    },
    {
      "template_id": "core_b1_if_present_will_future_03",
      "family_id": "core_b1_if_present_will_future_2",
      "pack_id": "core_b1",
      "theme": "core",
      "level": "B1",
      "pattern_id": "if_present_will_future",
      "primary_skill_id": "gerund_after_been",
      "skill_ids": [
        "gerund_after_been",
        "vocabulary"
      ],
      "exercise_types": [
        "translate_natural",
        "fill_blank",
        "build_sentence",
        "choose_best",
        "rewrite_natural",
        "listen_type",
        "speak_sentence"
      ],
      "slots": {
        "subject": "we",
        "object": "core_b1_question"
      },
      "constraints": [
        "subject_auxiliary_agreement",
        "level_allows_present_perfect_continuous"
      ],
      "distractor_strategies": [
        "wrong_word_order",
        "wrong_tense",
        "wrong_collocation"
      ],
      "sentence": "If we confirm the question, we will start tomorrow.",
      "source_locale": "pt-BR",
      "source_text_pt": "Se confirmarmos a pergunta, vamos começar amanhã.",
      "target_locale": "en",
      "expected_answers_en": [
        "If we confirm the question, we will start tomorrow."
      ],
      "accepted_variants_en": [
        "If we confirm the question, we'll start tomorrow."
      ],
      "explanation_pt": "Primeira condicional: if + presente, will + base.",
      "skill_targets": [
        "gerund_after_been"
      ],
      "pt": "Se confirmarmos a pergunta, vamos começar amanhã.",
      "ctx": "Contexto de base (nível B1).",
      "blank": "we",
      "wrong": "If we confirm the question, we will start tomorrow."
    },
    {
      "template_id": "core_b1_subject_modal_base_verb_04",
      "family_id": "core_b1_subject_modal_base_verb_3",
      "pack_id": "core_b1",
      "theme": "core",
      "level": "B1",
      "pattern_id": "subject_modal_base_verb",
      "primary_skill_id": "first_conditional",
      "skill_ids": [
        "first_conditional",
        "vocabulary"
      ],
      "exercise_types": [
        "translate_natural",
        "fill_blank",
        "build_sentence",
        "choose_best",
        "rewrite_natural",
        "listen_type",
        "speak_sentence"
      ],
      "slots": {
        "subject": "we",
        "object": "core_b1_idea"
      },
      "constraints": [
        "subject_auxiliary_agreement",
        "level_allows_present_perfect_continuous"
      ],
      "distractor_strategies": [
        "wrong_word_order",
        "wrong_tense",
        "wrong_collocation"
      ],
      "sentence": "I can update the idea today.",
      "source_locale": "pt-BR",
      "source_text_pt": "Eu posso atualizar a ideia hoje.",
      "target_locale": "en",
      "expected_answers_en": [
        "I can update the idea today."
      ],
      "accepted_variants_en": [],
      "explanation_pt": "Modal can + verbo na forma base.",
      "skill_targets": [
        "first_conditional"
      ],
      "pt": "Eu posso atualizar a ideia hoje.",
      "ctx": "Contexto de base (nível B1).",
      "blank": "can",
      "wrong": "I cans update the idea today."
    },
    {
      "template_id": "core_b1_subject_have_past_participle_yet_05",
      "family_id": "core_b1_subject_have_past_participle_yet_4",
      "pack_id": "core_b1",
      "theme": "core",
      "level": "B1",
      "pattern_id": "subject_have_past_participle_yet",
      "primary_skill_id": "question_auxiliary",
      "skill_ids": [
        "question_auxiliary",
        "vocabulary"
      ],
      "exercise_types": [
        "translate_natural",
        "fill_blank",
        "build_sentence",
        "choose_best",
        "rewrite_natural",
        "listen_type",
        "speak_sentence"
      ],
      "slots": {
        "subject": "we",
        "object": "core_b1_problem"
      },
      "constraints": [
        "subject_auxiliary_agreement",
        "level_allows_present_perfect_continuous"
      ],
      "distractor_strategies": [
        "wrong_word_order",
        "wrong_tense",
        "wrong_collocation"
      ],
      "sentence": "We have checked the problem already.",
      "source_locale": "pt-BR",
      "source_text_pt": "Nós já verificamos o problema.",
      "target_locale": "en",
      "expected_answers_en": [
        "We have checked the problem already."
      ],
      "accepted_variants_en": [
        "We've checked the problem already."
      ],
      "explanation_pt": "Present perfect com already.",
      "skill_targets": [
        "question_auxiliary"
      ],
      "pt": "Nós já verificamos o problema.",
      "ctx": "Contexto de base (nível B1).",
      "blank": "have",
      "wrong": "We have check the problem already."
    },
    {
      "template_id": "core_b1_subject_have_been_ving_object_duration_06",
      "family_id": "core_b1_subject_have_been_ving_object_duration_5",
      "pack_id": "core_b1",
      "theme": "core",
      "level": "B1",
      "pattern_id": "subject_have_been_ving_object_duration",
      "primary_skill_id": "collocation",
      "skill_ids": [
        "collocation",
        "vocabulary"
      ],
      "exercise_types": [
        "translate_natural",
        "fill_blank",
        "build_sentence",
        "choose_best",
        "rewrite_natural",
        "listen_type",
        "speak_sentence"
      ],
      "slots": {
        "subject": "we",
        "object": "core_b1_word"
      },
      "constraints": [
        "subject_auxiliary_agreement",
        "level_allows_present_perfect_continuous"
      ],
      "distractor_strategies": [
        "wrong_word_order",
        "wrong_tense",
        "wrong_collocation"
      ],
      "sentence": "They have been reviewing the word for two hours.",
      "source_locale": "pt-BR",
      "source_text_pt": "Eles estão revisando a palavra há duas horas.",
      "target_locale": "en",
      "expected_answers_en": [
        "They have been reviewing the word for two hours."
      ],
      "accepted_variants_en": [
        "They've been reviewing the word for two hours."
      ],
      "explanation_pt": "Present perfect continuous com duração (for).",
      "skill_targets": [
        "collocation"
      ],
      "pt": "Eles estão revisando a palavra há duas horas.",
      "ctx": "Contexto de base (nível B1).",
      "blank": "have",
      "wrong": "They have been reviewed the word for two hours."
    },
    {
      "template_id": "core_b1_if_present_will_future_07",
      "family_id": "core_b1_if_present_will_future_0",
      "pack_id": "core_b1",
      "theme": "core",
      "level": "B1",
      "pattern_id": "if_present_will_future",
      "primary_skill_id": "preposition",
      "skill_ids": [
        "preposition",
        "vocabulary"
      ],
      "exercise_types": [
        "translate_natural",
        "fill_blank",
        "build_sentence",
        "choose_best",
        "rewrite_natural",
        "listen_type",
        "speak_sentence"
      ],
      "slots": {
        "subject": "we",
        "object": "core_b1_name"
      },
      "constraints": [
        "subject_auxiliary_agreement",
        "level_allows_present_perfect_continuous"
      ],
      "distractor_strategies": [
        "wrong_word_order",
        "wrong_tense",
        "wrong_collocation"
      ],
      "sentence": "If we confirm the name, we will start tomorrow.",
      "source_locale": "pt-BR",
      "source_text_pt": "Se confirmarmos o nome, vamos começar amanhã.",
      "target_locale": "en",
      "expected_answers_en": [
        "If we confirm the name, we will start tomorrow."
      ],
      "accepted_variants_en": [
        "If we confirm the name, we'll start tomorrow."
      ],
      "explanation_pt": "Primeira condicional: if + presente, will + base.",
      "skill_targets": [
        "preposition"
      ],
      "pt": "Se confirmarmos o nome, vamos começar amanhã.",
      "ctx": "Contexto de base (nível B1).",
      "blank": "we",
      "wrong": "If we confirm the name, we will start tomorrow."
    },
    {
      "template_id": "core_b1_subject_modal_base_verb_08",
      "family_id": "core_b1_subject_modal_base_verb_1",
      "pack_id": "core_b1",
      "theme": "core",
      "level": "B1",
      "pattern_id": "subject_modal_base_verb",
      "primary_skill_id": "present_perfect",
      "skill_ids": [
        "present_perfect",
        "vocabulary"
      ],
      "exercise_types": [
        "translate_natural",
        "fill_blank",
        "build_sentence",
        "choose_best",
        "rewrite_natural",
        "listen_type",
        "speak_sentence"
      ],
      "slots": {
        "subject": "we",
        "object": "core_b1_number"
      },
      "constraints": [
        "subject_auxiliary_agreement",
        "level_allows_present_perfect_continuous"
      ],
      "distractor_strategies": [
        "wrong_word_order",
        "wrong_tense",
        "wrong_collocation"
      ],
      "sentence": "I can update the number today.",
      "source_locale": "pt-BR",
      "source_text_pt": "Eu posso atualizar o número hoje.",
      "target_locale": "en",
      "expected_answers_en": [
        "I can update the number today."
      ],
      "accepted_variants_en": [],
      "explanation_pt": "Modal can + verbo na forma base.",
      "skill_targets": [
        "present_perfect"
      ],
      "pt": "Eu posso atualizar o número hoje.",
      "ctx": "Contexto de base (nível B1).",
      "blank": "can",
      "wrong": "I cans update the number today."
    },
    {
      "template_id": "core_b1_subject_have_past_participle_yet_09",
      "family_id": "core_b1_subject_have_past_participle_yet_2",
      "pack_id": "core_b1",
      "theme": "core",
      "level": "B1",
      "pattern_id": "subject_have_past_participle_yet",
      "primary_skill_id": "present_perfect_continuous",
      "skill_ids": [
        "present_perfect_continuous",
        "vocabulary"
      ],
      "exercise_types": [
        "translate_natural",
        "fill_blank",
        "build_sentence",
        "choose_best",
        "rewrite_natural",
        "listen_type",
        "speak_sentence"
      ],
      "slots": {
        "subject": "we",
        "object": "core_b1_place"
      },
      "constraints": [
        "subject_auxiliary_agreement",
        "level_allows_present_perfect_continuous"
      ],
      "distractor_strategies": [
        "wrong_word_order",
        "wrong_tense",
        "wrong_collocation"
      ],
      "sentence": "We have checked the place already.",
      "source_locale": "pt-BR",
      "source_text_pt": "Nós já verificamos o lugar.",
      "target_locale": "en",
      "expected_answers_en": [
        "We have checked the place already."
      ],
      "accepted_variants_en": [
        "We've checked the place already."
      ],
      "explanation_pt": "Present perfect com already.",
      "skill_targets": [
        "present_perfect_continuous"
      ],
      "pt": "Nós já verificamos o lugar.",
      "ctx": "Contexto de base (nível B1).",
      "blank": "have",
      "wrong": "We have check the place already."
    },
    {
      "template_id": "core_b1_subject_have_been_ving_object_duration_10",
      "family_id": "core_b1_subject_have_been_ving_object_duration_3",
      "pack_id": "core_b1",
      "theme": "core",
      "level": "B1",
      "pattern_id": "subject_have_been_ving_object_duration",
      "primary_skill_id": "gerund_after_been",
      "skill_ids": [
        "gerund_after_been",
        "vocabulary"
      ],
      "exercise_types": [
        "translate_natural",
        "fill_blank",
        "build_sentence",
        "choose_best",
        "rewrite_natural",
        "listen_type",
        "speak_sentence"
      ],
      "slots": {
        "subject": "we",
        "object": "core_b1_time"
      },
      "constraints": [
        "subject_auxiliary_agreement",
        "level_allows_present_perfect_continuous"
      ],
      "distractor_strategies": [
        "wrong_word_order",
        "wrong_tense",
        "wrong_collocation"
      ],
      "sentence": "They have been reviewing the time for two hours.",
      "source_locale": "pt-BR",
      "source_text_pt": "Eles estão revisando o horário há duas horas.",
      "target_locale": "en",
      "expected_answers_en": [
        "They have been reviewing the time for two hours."
      ],
      "accepted_variants_en": [
        "They've been reviewing the time for two hours."
      ],
      "explanation_pt": "Present perfect continuous com duração (for).",
      "skill_targets": [
        "gerund_after_been"
      ],
      "pt": "Eles estão revisando o horário há duas horas.",
      "ctx": "Contexto de base (nível B1).",
      "blank": "have",
      "wrong": "They have been reviewed the time for two hours."
    },
    {
      "template_id": "core_b1_if_present_will_future_11",
      "family_id": "core_b1_if_present_will_future_4",
      "pack_id": "core_b1",
      "theme": "core",
      "level": "B1",
      "pattern_id": "if_present_will_future",
      "primary_skill_id": "first_conditional",
      "skill_ids": [
        "first_conditional",
        "vocabulary"
      ],
      "exercise_types": [
        "translate_natural",
        "fill_blank",
        "build_sentence",
        "choose_best",
        "rewrite_natural",
        "listen_type",
        "speak_sentence"
      ],
      "slots": {
        "subject": "we",
        "object": "core_b1_reason"
      },
      "constraints": [
        "subject_auxiliary_agreement",
        "level_allows_present_perfect_continuous"
      ],
      "distractor_strategies": [
        "wrong_word_order",
        "wrong_tense",
        "wrong_collocation"
      ],
      "sentence": "If we confirm the reason, we will start tomorrow.",
      "source_locale": "pt-BR",
      "source_text_pt": "Se confirmarmos o motivo, vamos começar amanhã.",
      "target_locale": "en",
      "expected_answers_en": [
        "If we confirm the reason, we will start tomorrow."
      ],
      "accepted_variants_en": [
        "If we confirm the reason, we'll start tomorrow."
      ],
      "explanation_pt": "Primeira condicional: if + presente, will + base.",
      "skill_targets": [
        "first_conditional"
      ],
      "pt": "Se confirmarmos o motivo, vamos começar amanhã.",
      "ctx": "Contexto de base (nível B1).",
      "blank": "we",
      "wrong": "If we confirm the reason, we will start tomorrow."
    },
    {
      "template_id": "core_b1_subject_modal_base_verb_12",
      "family_id": "core_b1_subject_modal_base_verb_5",
      "pack_id": "core_b1",
      "theme": "core",
      "level": "B1",
      "pattern_id": "subject_modal_base_verb",
      "primary_skill_id": "question_auxiliary",
      "skill_ids": [
        "question_auxiliary",
        "vocabulary"
      ],
      "exercise_types": [
        "translate_natural",
        "fill_blank",
        "build_sentence",
        "choose_best",
        "rewrite_natural",
        "listen_type",
        "speak_sentence"
      ],
      "slots": {
        "subject": "we",
        "object": "core_b1_example"
      },
      "constraints": [
        "subject_auxiliary_agreement",
        "level_allows_present_perfect_continuous"
      ],
      "distractor_strategies": [
        "wrong_word_order",
        "wrong_tense",
        "wrong_collocation"
      ],
      "sentence": "I can update the example today.",
      "source_locale": "pt-BR",
      "source_text_pt": "Eu posso atualizar o exemplo hoje.",
      "target_locale": "en",
      "expected_answers_en": [
        "I can update the example today."
      ],
      "accepted_variants_en": [],
      "explanation_pt": "Modal can + verbo na forma base.",
      "skill_targets": [
        "question_auxiliary"
      ],
      "pt": "Eu posso atualizar o exemplo hoje.",
      "ctx": "Contexto de base (nível B1).",
      "blank": "can",
      "wrong": "I cans update the example today."
    }
  ],
  "collocations": [
    {
      "collocation_id": "core_b1_plan_chunk",
      "pack_id": "core_b1",
      "theme": "core",
      "level": "B1",
      "canonical": "make a plan",
      "translation_pt": "plano",
      "invalid_variants": [
        "do a plan"
      ],
      "skill_id": "collocation"
    },
    {
      "collocation_id": "core_b1_answer_chunk",
      "pack_id": "core_b1",
      "theme": "core",
      "level": "B1",
      "canonical": "check the answer",
      "translation_pt": "resposta",
      "invalid_variants": [
        "do the answer"
      ],
      "skill_id": "collocation"
    },
    {
      "collocation_id": "core_b1_question_chunk",
      "pack_id": "core_b1",
      "theme": "core",
      "level": "B1",
      "canonical": "make a question",
      "translation_pt": "pergunta",
      "invalid_variants": [
        "do a question"
      ],
      "skill_id": "collocation"
    },
    {
      "collocation_id": "core_b1_idea_chunk",
      "pack_id": "core_b1",
      "theme": "core",
      "level": "B1",
      "canonical": "check the idea",
      "translation_pt": "ideia",
      "invalid_variants": [
        "do the idea"
      ],
      "skill_id": "collocation"
    },
    {
      "collocation_id": "core_b1_problem_chunk",
      "pack_id": "core_b1",
      "theme": "core",
      "level": "B1",
      "canonical": "make a problem",
      "translation_pt": "problema",
      "invalid_variants": [
        "do a problem"
      ],
      "skill_id": "collocation"
    },
    {
      "collocation_id": "core_b1_word_chunk",
      "pack_id": "core_b1",
      "theme": "core",
      "level": "B1",
      "canonical": "check the word",
      "translation_pt": "palavra",
      "invalid_variants": [
        "do the word"
      ],
      "skill_id": "collocation"
    },
    {
      "collocation_id": "core_b1_name_chunk",
      "pack_id": "core_b1",
      "theme": "core",
      "level": "B1",
      "canonical": "make a name",
      "translation_pt": "nome",
      "invalid_variants": [
        "do a name"
      ],
      "skill_id": "collocation"
    },
    {
      "collocation_id": "core_b1_number_chunk",
      "pack_id": "core_b1",
      "theme": "core",
      "level": "B1",
      "canonical": "check the number",
      "translation_pt": "número",
      "invalid_variants": [
        "do the number"
      ],
      "skill_id": "collocation"
    },
    {
      "collocation_id": "core_b1_place_chunk",
      "pack_id": "core_b1",
      "theme": "core",
      "level": "B1",
      "canonical": "make a place",
      "translation_pt": "lugar",
      "invalid_variants": [
        "do a place"
      ],
      "skill_id": "collocation"
    }
  ]
}
